{"expireTime":9007200828655365000,"key":"transformer-remark-markdown-ast-461f4b16ddbb31807d18211316525ced--","val":{"type":"root","children":[{"type":"heading","depth":1,"children":[{"type":"text","value":"Sponsors","position":{"start":{"line":2,"column":3,"offset":3},"end":{"line":2,"column":11,"offset":11},"indent":[]}}],"position":{"start":{"line":2,"column":1,"offset":1},"end":{"line":2,"column":11,"offset":11},"indent":[]}},{"type":"heading","depth":2,"children":[{"type":"text","value":"Galaxy Sponsors","position":{"start":{"line":5,"column":4,"offset":17},"end":{"line":5,"column":19,"offset":32},"indent":[]}}],"position":{"start":{"line":5,"column":1,"offset":14},"end":{"line":5,"column":19,"offset":32},"indent":[]}},{"type":"paragraph","children":[{"type":"image","title":"Aerospace at Illinois","url":"https://iris.ae.illinois.edu/files/2018/09/AeroLogo.png","alt":"Aerospace at Illinois","position":{"start":{"line":7,"column":1,"offset":34},"end":{"line":7,"column":106,"offset":139},"indent":[]}}],"position":{"start":{"line":7,"column":1,"offset":34},"end":{"line":7,"column":106,"offset":139},"indent":[]}},{"type":"paragraph","children":[{"type":"text","value":"Illinois Robotics in Space would like to thank our home department, the Department of Aerospace Engineering for their continued support. ","position":{"start":{"line":9,"column":1,"offset":141},"end":{"line":9,"column":138,"offset":278},"indent":[]}}],"position":{"start":{"line":9,"column":1,"offset":141},"end":{"line":9,"column":138,"offset":278},"indent":[]}},{"type":"paragraph","children":[{"type":"image","title":"Illinois Space Grant Consortium","url":"https://iris.ae.illinois.edu/files/2018/09/ISGC.png","alt":"Illinois Space Grant Consortium","position":{"start":{"line":11,"column":1,"offset":280},"end":{"line":11,"column":122,"offset":401},"indent":[]}},{"type":"text","value":"\n","position":{"start":{"line":11,"column":122,"offset":401},"end":{"line":12,"column":1,"offset":402},"indent":[1]}},{"type":"image","title":null,"url":"https://iris.ae.illinois.edu/files/2015/10/SorfLogo_rztquf-300x145.jpg\"Funded by SORF\"","alt":"Funded by SORF","position":{"start":{"line":12,"column":1,"offset":402},"end":{"line":12,"column":106,"offset":507},"indent":[]}}],"position":{"start":{"line":11,"column":1,"offset":280},"end":{"line":12,"column":106,"offset":507},"indent":[1]}},{"type":"paragraph","children":[{"type":"text","value":"We also would like to acknowledge the support of the Illinois Space Grant Consortium, and the Student Organization Registration Fund.","position":{"start":{"line":14,"column":1,"offset":509},"end":{"line":14,"column":134,"offset":642},"indent":[]}}],"position":{"start":{"line":14,"column":1,"offset":509},"end":{"line":14,"column":134,"offset":642},"indent":[]}},{"type":"heading","depth":2,"children":[{"type":"text","value":"Star Sponsors","position":{"start":{"line":15,"column":4,"offset":646},"end":{"line":15,"column":17,"offset":659},"indent":[]}}],"position":{"start":{"line":15,"column":1,"offset":643},"end":{"line":15,"column":17,"offset":659},"indent":[]}},{"type":"paragraph","children":[{"type":"text","value":"Coming soon.","position":{"start":{"line":16,"column":1,"offset":660},"end":{"line":16,"column":13,"offset":672},"indent":[]}}],"position":{"start":{"line":16,"column":1,"offset":660},"end":{"line":16,"column":13,"offset":672},"indent":[]}},{"type":"heading","depth":2,"children":[{"type":"text","value":"Planet Sponsors","position":{"start":{"line":18,"column":4,"offset":677},"end":{"line":18,"column":19,"offset":692},"indent":[]}}],"position":{"start":{"line":18,"column":1,"offset":674},"end":{"line":18,"column":19,"offset":692},"indent":[]}},{"type":"paragraph","children":[{"type":"text","value":"Coming soon.","position":{"start":{"line":19,"column":1,"offset":693},"end":{"line":19,"column":13,"offset":705},"indent":[]}}],"position":{"start":{"line":19,"column":1,"offset":693},"end":{"line":19,"column":13,"offset":705},"indent":[]}},{"type":"heading","depth":2,"children":[{"type":"text","value":"Lunar Sponsors","position":{"start":{"line":21,"column":4,"offset":711},"end":{"line":21,"column":18,"offset":725},"indent":[]}}],"position":{"start":{"line":21,"column":1,"offset":708},"end":{"line":21,"column":18,"offset":725},"indent":[]}},{"type":"paragraph","children":[{"type":"text","value":"You?","position":{"start":{"line":22,"column":1,"offset":726},"end":{"line":22,"column":5,"offset":730},"indent":[]}}],"position":{"start":{"line":22,"column":1,"offset":726},"end":{"line":22,"column":5,"offset":730},"indent":[]}},{"type":"paragraph","children":[{"type":"text","value":"We have the talent. We have the passion. We need help from generous companies willing to support Illinois Robotics in Space as we build the best in autonomous and innovative mining robots.","position":{"start":{"line":24,"column":1,"offset":732},"end":{"line":24,"column":189,"offset":920},"indent":[]}}],"position":{"start":{"line":24,"column":1,"offset":732},"end":{"line":24,"column":189,"offset":920},"indent":[]}},{"type":"paragraph","children":[{"type":"text","value":"Interested in supporting our team? We’d love to talk to you! The best way to learn everything to know about sponsorship is through our Sponsorship Packet. Take a look, and contact us at iris.uiuc@gmail.com if you have any questions!","position":{"start":{"line":26,"column":1,"offset":922},"end":{"line":26,"column":233,"offset":1154},"indent":[]}}],"position":{"start":{"line":26,"column":1,"offset":922},"end":{"line":26,"column":233,"offset":1154},"indent":[]}}],"position":{"start":{"line":1,"column":1,"offset":0},"end":{"line":27,"column":1,"offset":1155}}}}